naughty/__init__.py
naughty/subdomains.py
naughty-0.0.2.dist-info/DESCRIPTION.rst
naughty-0.0.2.dist-info/METADATA
naughty-0.0.2.dist-info/RECORD
naughty-0.0.2.dist-info/WHEEL
naughty-0.0.2.dist-info/metadata.json
naughty-0.0.2.dist-info/top_level.txt
