Metadata-Version: 2.0
Name: naughty
Version: 0.0.2
Summary: A collection of lists of naughty words for use in software development
Home-page: https://github.com/wildfoundry/naughtywords/
Author: WildFoundry Ltd
Author-email: info@wildfoundry.com
License: LGPL
Platform: UNKNOWN
Classifier: Development Status :: 2 - Pre-Alpha
Classifier: Intended Audience :: Developers
Classifier: License :: OSI Approved :: GNU Lesser General Public License v3 (LGPLv3)
Classifier: Natural Language :: English
Classifier: Programming Language :: Python :: 2
Classifier: Programming Language :: Python :: 3
